MANIFEST.in
README.rst
setup.cfg
setup.py
Studio.egg-info/PKG-INFO
Studio.egg-info/SOURCES.txt
Studio.egg-info/dependency_links.txt
Studio.egg-info/entry_points.txt
Studio.egg-info/not-zip-safe
Studio.egg-info/paster_plugins.txt
Studio.egg-info/requires.txt
Studio.egg-info/top_level.txt
studio/__init__.py
studio/websetup.py
studio/config/__init__.py
studio/config/deployment.ini_tmpl
studio/config/environment.py
studio/config/installer.py
studio/config/middleware.py
studio/config/routing.py
studio/controllers/__init__.py
studio/controllers/datasources.py
studio/controllers/datastores.py
studio/controllers/error.py
studio/controllers/layertemplates.py
studio/controllers/main.py
studio/controllers/mapfiles.py
studio/i18n/en/LC_MESSAGES/studio.mo
studio/i18n/fr/LC_MESSAGES/studio.mo
studio/lib/__init__.py
studio/lib/app_globals.py
studio/lib/archivefile.py
studio/lib/auth.py
studio/lib/base.py
studio/lib/colorthemer.py
studio/lib/datasource_discovery.py
studio/lib/helpers.py
studio/lib/mapscriptutils.py
studio/lib/mapserializer.py
studio/lib/os_utils.py
studio/lib/provisionning.py
studio/lib/sa_types.py
studio/lib/buildjs/__init__.py
studio/lib/buildjs/jsmin.py
studio/lib/buildjs/merge_js.py
studio/model/__init__.py
studio/model/meta.py
studio/public/upload.html
studio/public/css/global.css
studio/public/css/signin.css
studio/public/images/add.gif
studio/public/images/arrow_left.gif
studio/public/images/database.png
studio/public/images/delete.gif
studio/public/images/folderclose.gif
studio/public/images/information.gif
studio/public/images/move_down.png
studio/public/images/move_left.png
studio/public/images/move_right.png
studio/public/images/move_up.png
studio/public/images/panel-close.gif
studio/public/images/s.gif
studio/public/images/script_save.gif
studio/public/images/studio.png
studio/public/images/wand.gif
studio/public/js/Ext/ext-all-debug.js
studio/public/js/Ext/ext-all.js
studio/public/js/Ext/adapter/ext/ext-base.js
studio/public/js/Ext/resources/resources.jsb
studio/public/js/Ext/resources/css/README.txt
studio/public/js/Ext/resources/css/borders.css
studio/public/js/Ext/resources/css/box.css
studio/public/js/Ext/resources/css/button.css
studio/public/js/Ext/resources/css/combo.css
