Metadata-Version: 1.0
Name: Studio
Version: 0.5.1
Summary: Web-based administration interface for MapServer
Home-page: http://camptocamp.github.com/Studio/
Author: Camptocamp
Author-email: studio-discuss@googlegroups.com
License: GPLv3
Keywords: GIS management mapserver
Platform: UNKNOWN
Classifier: Development Status :: 4 - Beta
Classifier: Intended Audience :: Science/Research
Classifier: License :: OSI Approved :: GNU General Public License (GPL)
Classifier: Operating System :: OS Independent
Classifier: Programming Language :: Python
Classifier: Framework :: Pylons
Classifier: Topic :: Scientific/Engineering :: GIS
Classifier: Topic :: Internet :: WWW/HTTP
Classifier: Topic :: Internet :: WWW/HTTP :: Dynamic Content
Classifier: Topic :: Internet :: WWW/HTTP :: WSGI
